MANIFEST.in
setup.cfg
setup.py
incapsula/__init__.py
incapsula/config.py
incapsula/methods.py
incapsula/navigator.json
incapsula/requests_.py
incapsula/scrapy_.py
incapsula/serialize.html
incapsula/test.py
incapsula_cracker.egg-info/PKG-INFO
incapsula_cracker.egg-info/SOURCES.txt
incapsula_cracker.egg-info/dependency_links.txt
incapsula_cracker.egg-info/requires.txt
incapsula_cracker.egg-info/top_level.txt