Metadata-Version: 1.0
Name: incapsula-cracker
Version: 0.1.3
Summary: A way to bypass incapsula robot checks when using requests or scrapy.
Home-page: https://github.com/ziplokk1/incapsula-cracker
Author: Mark Sanders
Author-email: sdscdeveloper@gmail.com
License: LICENSE.txt
Platform: UNKNOWN
